ccloc/__init__.py
ccloc/__main__.py
ccloc/cli.py
ccloc/counter.py
ccloc/formatter.py
ccloc-0.1.6.dist-info/METADATA
ccloc-0.1.6.dist-info/WHEEL
ccloc-0.1.6.dist-info/entry_points.txt
ccloc-0.1.6.dist-info/licenses/LICENSE.md
ccloc-0.1.6.dist-info/RECORD
