Metadata-Version: 2.4
Name: ccloc
Version: 0.1.6
Summary: Just Count Total Line Of Code
Author-email: Chuong Ho <chuongpqvn@gmail.com>
License-File: LICENSE.md
Requires-Python: >=3.10
Requires-Dist: click>=8.3.1
Requires-Dist: rich>=14.2.0
